cli_requests/__init__.py
cli_requests/__main__.py
cli_requests/argparser.py
cli_requests/colorizer.py
cli_requests/exceptions.py
cli_requests/requester.py
cli_requests-0.2.1.dist-info/LICENSE
cli_requests-0.2.1.dist-info/METADATA
cli_requests-0.2.1.dist-info/WHEEL
cli_requests-0.2.1.dist-info/entry_points.txt
cli_requests-0.2.1.dist-info/top_level.txt
cli_requests-0.2.1.dist-info/RECORD
