Metadata-Version: 2.1
Name: cli-requests
Version: 0.2.1
Summary: simple cli program to send requests
Home-page: https://github.com/Sabberian/cli_requests
Author: sabberian
License: MIT
Platform: UNKNOWN
Classifier: License :: OSI Approved :: MIT License
Classifier: Programming Language :: Python :: 3
Requires-Python: >=3.8
License-File: LICENSE
Requires-Dist: colorama (==0.4.6)
Requires-Dist: requests (==2.31.0)
